reolink_aio/__init__.py
reolink_aio/api.py
reolink_aio/const.py
reolink_aio/enums.py
reolink_aio/exceptions.py
reolink_aio/py.typed
reolink_aio/software_version.py
reolink_aio/templates.py
reolink_aio/typings.py
reolink_aio/utils.py
reolink_aio/baichuan/__init__.py
reolink_aio/baichuan/baichuan.py
reolink_aio/baichuan/tcp_protocol.py
reolink_aio/baichuan/util.py
reolink_aio/baichuan/xmls.py
reolink_aio-0.18.2.dist-info/licenses/LICENSE
reolink_aio-0.18.2.dist-info/METADATA
reolink_aio-0.18.2.dist-info/WHEEL
reolink_aio-0.18.2.dist-info/top_level.txt
reolink_aio-0.18.2.dist-info/RECORD
