Metadata-Version: 2.4
Name: reolink_aio
Version: 0.18.2
Summary: Reolink NVR/cameras API package
Home-page: https://github.com/starkillerOG/reolink_aio
Author: starkillerOG
Author-email: starkiller.og@gmail.com
License: MIT
Platform: any
Classifier: Development Status :: 5 - Production/Stable
Classifier: Intended Audience :: Developers
Classifier: License :: OSI Approved :: MIT License
Classifier: Operating System :: OS Independent
Classifier: Topic :: Software Development :: Libraries
Classifier: Topic :: Home Automation
Classifier: Programming Language :: Python
Classifier: Programming Language :: Python :: 3.11
Classifier: Programming Language :: Python :: 3.12
Classifier: Programming Language :: Python :: 3.13
Classifier: Programming Language :: Python :: 3.14
Requires-Python: >=3.11
License-File: LICENSE
Requires-Dist: aiohttp
Requires-Dist: aiortsp
Requires-Dist: orjson
Requires-Dist: pycryptodomex
Requires-Dist: typing_extensions
Dynamic: author
Dynamic: author-email
Dynamic: classifier
Dynamic: description
Dynamic: description-content-type
Dynamic: home-page
Dynamic: license
Dynamic: license-file
Dynamic: platform
Dynamic: requires-dist
Dynamic: requires-python
Dynamic: summary
